<annotation>
	<folder>data</folder>
	<filename>4240.jpg</filename>
	<path>/content/drive/MyDrive/data/4240.jpg</path>
	<source>
		<database>Unknown</database>
	</source>
	<size>
		<width>400</width>
		<height>600</height>
		<depth>3</depth>
	</size>
	<segmented>0</segmented>
	<object>
		<name>shirt</name>
		<pose>Unspecified</pose>
		<truncated>0</truncated>
		<difficult>0</difficult>
		<bndbox>
			<xmin>112</xmin>
			<ymin>189</ymin>
			<xmax>169</xmax>
			<ymax>302</ymax>
		</bndbox>
	</object>
	<object>
		<name>bag</name>
		<pose>Unspecified</pose>
		<truncated>0</truncated>
		<difficult>0</difficult>
		<bndbox>
			<xmin>170</xmin>
			<ymin>275</ymin>
			<xmax>242</xmax>
			<ymax>351</ymax>
		</bndbox>
	</object>
	<object>
		<name>shoe</name>
		<pose>Unspecified</pose>
		<truncated>0</truncated>
		<difficult>0</difficult>
		<bndbox>
			<xmin>88</xmin>
			<ymin>500</ymin>
			<xmax>232</xmax>
			<ymax>570</ymax>
		</bndbox>
	</object>
	<object>
		<name>shorts</name>
		<pose>Unspecified</pose>
		<truncated>0</truncated>
		<difficult>0</difficult>
		<bndbox>
			<xmin>116</xmin>
			<ymin>281</ymin>
			<xmax>156</xmax>
			<ymax>363</ymax>
		</bndbox>
	</object>
	<object>
		<name>sunglass</name>
		<pose>Unspecified</pose>
		<truncated>0</truncated>
		<difficult>0</difficult>
		<bndbox>
			<xmin>123</xmin>
			<ymin>96</ymin>
			<xmax>154</xmax>
			<ymax>131</ymax>
		</bndbox>
	</object>
</annotation>
